fastapi_users_ormar_ext/__init__.py
fastapi_users_ormar_ext/py.typed
fastapi_users_ormar_ext-0.1.2.dist-info/LICENSE
fastapi_users_ormar_ext-0.1.2.dist-info/METADATA
fastapi_users_ormar_ext-0.1.2.dist-info/WHEEL
fastapi_users_ormar_ext-0.1.2.dist-info/RECORD
