Metadata-Version: 2.1
Name: fastapi-users-ormar-ext
Version: 0.1.2
Summary: Use ormar for your fastapi-users project.
License: MIT
Author: Jegor Kitskerkin
Author-email: jegor.kitskerkin@gmail.com
Requires-Python: >=3.9,<4.0
Classifier: License :: OSI Approved :: MIT License
Classifier: Programming Language :: Python :: 3
Classifier: Programming Language :: Python :: 3.9
Classifier: Programming Language :: Python :: 3.10
Classifier: Programming Language :: Python :: 3.11
Requires-Dist: fastapi-users (>=10.2.0)
Requires-Dist: ormar (>=0.11.0)
